ipc_parser/__init__.py
ipc_parser/parser.py
ipc_parser-0.1.1.dist-info/LICENSE
ipc_parser-0.1.1.dist-info/METADATA
ipc_parser-0.1.1.dist-info/WHEEL
ipc_parser-0.1.1.dist-info/top_level.txt
ipc_parser-0.1.1.dist-info/RECORD
