Metadata-Version: 2.1
Name: ipc_parser
Version: 0.1.1
Summary: Parsing XML International Patent Classifications (IPC)
Home-page: https://github.com/ShayanSadeghi/ipc_parser
Author: Shayan Sadeghi
Author-email: ShayanSadeghi1996@gmail.com
Keywords: ipc,patent,wipo
Classifier: Programming Language :: Python :: 3
Classifier: License :: OSI Approved :: Apache Software License
Classifier: Operating System :: OS Independent
Requires-Python: >=3.6
License-File: LICENSE
Requires-Dist: pandas
Requires-Dist: lxml
